AUTHORS
ChangeLog
README
requirements.txt
setup.cfg
setup.py
tox.ini
tests/logger.yml
tests/logger_test.py
tests/zkclient_test.py
zkclient/__init__.py
zkclient.egg-info/PKG-INFO
zkclient.egg-info/SOURCES.txt
zkclient.egg-info/dependency_links.txt
zkclient.egg-info/not-zip-safe
zkclient.egg-info/requires.txt
zkclient.egg-info/top_level.txt