Metadata-Version: 1.1
Name: zkclient
Version: v1.3
Summary: wrapper zkclient for python
Home-page: https://github.com/airhuman/py_zkclient.git
Author: Michael
Author-email: liyong19861014@gmail.com
License: UNKNOWN
Platform: UNKNOWN
Classifier: Intended Audience :: Information Technology
Classifier: Operating System :: POSIX :: Linux
Classifier: Programming Language :: Python
Classifier: Programming Language :: Python :: 2
Classifier: Programming Language :: Python :: 2.7
Classifier: Programming Language :: Python :: 2.6
